{
  "project_info": {
    "project_number": "1029496202796",
    "project_id": "huskis-79721",
    "storage_bucket": "huskis-79721.appspot.com"
  },
  "client": [
    {
      "client_info": {
        "mobilesdk_app_id": "1:1029496202796:android:5b95cc686bee839dffd389",
        "android_client_info": {
          "package_name": "com.example.huskis"
        }
      },
      "oauth_client": [
        {
          "client_id": "1029496202796-mdkj0jrvtqpnenfhdcdh7ep5205avc0l.apps.googleusercontent.com",
          "client_type": 3
        }
      ],
      "api_key": [
        {
          "current_key": "AIzaSyBDTgkCeBNGFdzgZt9O-wDUwAVxFWCtvoU"
        }
      ],
      "services": {
        "appinvite_service": {
          "other_platform_oauth_client": [
            {
              "client_id": "1029496202796-mdkj0jrvtqpnenfhdcdh7ep5205avc0l.apps.googleusercontent.com",
              "client_type": 3
            }
          ]
        }
      }
    }
  ],
  "configuration_version": "1"
}